pdf2png/__init__.py
pdf2png/server.py
mseep_pdf2png-0.1.4.dist-info/METADATA
mseep_pdf2png-0.1.4.dist-info/WHEEL
mseep_pdf2png-0.1.4.dist-info/entry_points.txt
mseep_pdf2png-0.1.4.dist-info/top_level.txt
mseep_pdf2png-0.1.4.dist-info/RECORD
